docs/_static/melusine.png
docs/_static/segmentation.png
docs/docs_src/__init__.py
docs/docs_src/BasicClassification/__init__.py
docs/docs_src/BasicClassification/tutorial001.py
docs/docs_src/Configurations/__init__.py
docs/docs_src/Configurations/tutorial001.py
docs/docs_src/GettingStarted/__init__.py
docs/docs_src/GettingStarted/tutorial001.py
docs/docs_src/GettingStarted/tutorial002.py
docs/docs_src/MelusineDetectors/__init__.py
docs/docs_src/MelusineDetectors/tutorial001.py
docs/docs_src/MelusineDetectors/tutorial002.py
docs/docs_src/MelusineDetectors/tutorial003.py
docs/docs_src/MelusineDetectors/tutorial004.py
docs/docs_src/MelusinePipeline/__init__.py
docs/docs_src/MelusinePipeline/tutorial001.py
docs/docs_src/MelusineRegex/__init__.py
docs/docs_src/MelusineRegex/tutorial001.py
docs/docs_src/MelusineTransformers/__init__.py
docs/docs_src/MelusineTransformers/tutorial001.py
docs/docs_src/Models/__init__.py
docs/docs_src/Models/tutorial001.py
melusine/__init__.py
melusine/_config.py
melusine/base.py
melusine/detectors.py
melusine/message.py
melusine/pipeline.py
melusine/processors.py
melusine/backend/__init__.py
melusine/backend/active_backend.py
melusine/backend/base_backend.py
melusine/backend/dict_backend.py
melusine/backend/pandas_backend.py
melusine/conf/global.yaml
melusine/conf/models.yaml
melusine/conf/shared.yaml
melusine/conf/detectors/emergency_detector.yaml
melusine/conf/detectors/reply_detector.yaml
melusine/conf/detectors/thanks_detector.yaml
melusine/conf/detectors/transfer_detector.yaml
melusine/conf/detectors/vacation_reply_detector.yaml
melusine/conf/pipelines/demo_pipeline.yaml
melusine/conf/pipelines/expeditor_pipeline.yaml
melusine/conf/pipelines/my_pipeline.yaml
melusine/conf/pipelines/pipeline_selection.yaml
melusine/conf/pipelines/preprocessing_pipeline.yaml
melusine/conf/pipelines/recipients_pipeline.yaml
melusine/conf/pipelines/reply_pipeline.yaml
melusine/conf/pipelines/thanks_pipeline.yaml
melusine-3.2.0.dist-info/AUTHORS.rst
melusine-3.2.0.dist-info/LICENSE
melusine-3.2.0.dist-info/METADATA
melusine-3.2.0.dist-info/WHEEL
melusine-3.2.0.dist-info/top_level.txt
melusine-3.2.0.dist-info/RECORD
