Metadata-Version: 2.2
Name: melusine
Version: 3.2.0
Summary: Melusine is a high-level library for emails processing
Author: Tiphaine Fabre, Sacha Samama, Antoine Simoulin
Author-email: Hugo Perrier <hugorperrier@gmail.com>
License: Apache Software License 2.0
Keywords: nlp,email,courriel,text,data-science,machine-learning,natural-language-processing
Classifier: Operating System :: OS Independent
Classifier: Programming Language :: Python :: 3
Classifier: Programming Language :: Python
Classifier: Topic :: Software Development :: Libraries :: Python Modules
Classifier: Topic :: Software Development :: Libraries
Classifier: Topic :: Software Development
Classifier: Topic :: Communications :: Email
Classifier: Typing :: Typed
Classifier: Development Status :: 4 - Beta
Classifier: Intended Audience :: Developers
Classifier: License :: OSI Approved :: Apache Software License
Classifier: Programming Language :: Python :: 3 :: Only
Classifier: Programming Language :: Python :: 3.8
Classifier: Programming Language :: Python :: 3.9
Classifier: Programming Language :: Python :: 3.10
Classifier: Programming Language :: Python :: 3.11
Classifier: Programming Language :: Python :: 3.12
Classifier: Natural Language :: English
Requires-Python: >=3.8
License-File: LICENSE
License-File: AUTHORS.rst
Requires-Dist: arrow
Requires-Dist: pandas>2
Requires-Dist: scikit-learn>=1
Requires-Dist: tqdm>=4.34
Requires-Dist: omegaconf>=2.0
Provides-Extra: dev
Requires-Dist: tox; extra == "dev"
Requires-Dist: pre-commit; extra == "dev"
Requires-Dist: black; extra == "dev"
Requires-Dist: flake8; extra == "dev"
Requires-Dist: isort; extra == "dev"
Requires-Dist: mypy; extra == "dev"
Requires-Dist: pytest; extra == "dev"
Requires-Dist: coverage; extra == "dev"
Requires-Dist: build; extra == "dev"
Requires-Dist: ruff; extra == "dev"
Provides-Extra: test
Requires-Dist: pytest; extra == "test"
Requires-Dist: coverage; extra == "test"
Requires-Dist: pytest-cov; extra == "test"
Requires-Dist: google-auth-oauthlib; extra == "test"
Requires-Dist: google-api-python-client; extra == "test"
Provides-Extra: transformers
Requires-Dist: transformers>4; extra == "transformers"
Provides-Extra: connectors
Requires-Dist: exchangelib; extra == "connectors"
Provides-Extra: gmail
Requires-Dist: google-auth-oauthlib; extra == "gmail"
Requires-Dist: google-api-python-client; extra == "gmail"
Provides-Extra: docs
Requires-Dist: mkdocs; extra == "docs"
Requires-Dist: markdown; extra == "docs"
Requires-Dist: mkdocs-material; extra == "docs"
Requires-Dist: mdx-include; extra == "docs"
